cdk_serverless_api/__init__.py
cdk_serverless_api/py.typed
cdk_serverless_api/_jsii/__init__.py
cdk_serverless_api/_jsii/cdk-serverless-api@0.0.3.jsii.tgz
cdk_serverless_api-0.0.3.dist-info/METADATA
cdk_serverless_api-0.0.3.dist-info/WHEEL
cdk_serverless_api-0.0.3.dist-info/top_level.txt
cdk_serverless_api-0.0.3.dist-info/RECORD
